{"screen_name":{"0":"informate_infor"},"tweet_id":{"0":1336461679966760961},"is_retweet":{"0":false},"text":{"0":"17.500 asesinados m\u00e1s de lo habitual...que como sabemos la democracia espa\u00f1ola se lleva por delante 34.000 DEPENDIENTES CADA A\u00d1O esperando las ayudas por dependencia. El genocidio legalizado y silenciado...aunque no del todo. Pero lo q mata es 'EL BICHO'\nhttps:\/\/t.co\/4nuLVJGK7A"},"user_verified":{"0":false},"created_at":{"0":"2020-12-09 00:04:29"},"retweet_count":{"0":15},"favorite_count":{"0":18},"user_location":{"0":""},"user_url":{"0":"https:\/\/t.co\/6IpnkGlun9"},"entities":{"0":{"hashtags":[],"symbols":[],"user_mentions":[],"urls":[{"url":"https:\/\/t.co\/4nuLVJGK7A","expanded_url":"https:\/\/www.lasexta.com\/noticias\/sociedad\/mas-51500-dependientes-han-fallecido-que-ano-esperando-ayudas_202012085fcfc76755a6d40001e8d03a.html","display_url":"lasexta.com\/noticias\/socie\u2026","indices":[255,278]}]}}}