{"screen_name":{"0":"tiramillas","1":"tiramillas","2":"tiramillas","3":"tiramillas","4":"tiramillas","5":"tiramillas","6":"tiramillas","7":"tiramillas","8":"tiramillas","9":"tiramillas","10":"tiramillas","11":"tiramillas","12":"tiramillas","13":"tiramillas","14":"tiramillas"},"tweet_id":{"0":1335007909642702849,"1":1334932571629694976,"2":1334861571961589765,"3":1334857576748642305,"4":1334855292417400832,"5":1334851744413659136,"6":1334850055094886400,"7":1334849638537572353,"8":1334846532902932480,"9":1334840861574754307,"10":1334838227698671618,"11":1334814038849708033,"12":1334786483413262336,"13":1334762146266279936,"14":1334760809793277952},"is_retweet":{"0":false,"1":false,"2":false,"3":false,"4":false,"5":false,"6":false,"7":false,"8":false,"9":false,"10":false,"11":false,"12":false,"13":false,"14":false},"text":{"0":"As\u00ed es el jersey navide\u00f1o de Lidl que se ha agotado online en un d\u00eda\nhttps:\/\/t.co\/TRRZU430Do","1":"El espectacular y dram\u00e1tico aterrizaje de una avioneta en plena autopista \nhttps:\/\/t.co\/MCGm0rq0uJ","2":"Estas son las autonom\u00edas que no estar\u00e1n confinadas de momento y las medidas de toda Espa\u00f1a por el Puente de la Constituci\u00f3n :backhand_index_pointing_down: https:\/\/t.co\/26EkOUHXEg","3":"La \u00faltima foto de @PilarRubio_ en lencer\u00eda con la que deslumbra Instagram :star-struck: https:\/\/t.co\/aTiV0U3SnE","4":":film_projector: 'El Padrino ep\u00edlogo: La muerte de Michael Corleone', el final de la trilog\u00eda como la imagin\u00f3 su director, llega hoy a los cines https:\/\/t.co\/B97U8NgpbI","5":":magnifying_glass_tilted_left: La CIA publica un acertijo en Twitter para captar a las mentes m\u00e1s brillantes: \u00bfLo puedes resolver? https:\/\/t.co\/5tz3utcydo","6":":microbe: \u00bfQu\u00e9 es el norovirus, el nuevo virus que amenaza desde China? \u00bfQu\u00e9 s\u00edntomas tiene y c\u00f3mo te puedes contagiar? https:\/\/t.co\/Q3tGkvkxJW","7":":syringe: Moderna asegura que su vacuna contra el Covid 19 tiene eficiencia prolongada https:\/\/t.co\/LKF5HwBoA2","8":"Rafael Amargo, en libertad tras dos d\u00edas detenido: \"Ha sido un espect\u00e1culo innecesario, Pablo Escobar hab\u00eda uno\" https:\/\/t.co\/JCMhBcAFJt","9":":thinking_face: 'Jes\u00e9 Rodr\u00edguez, \u00bfde jugar en el Real Madrid y el PSG a fichar por Mediaset?' :writing_hand_selector: https:\/\/t.co\/PtNgdIdDRs La opini\u00f3n de @J_Fdez_Borrell","10":":collision: Pol\u00e9mica en Pasapalabra: acusan en redes a Roberto Leal de ayudar a un concursante en pleno 'rosco' https:\/\/t.co\/LvNTdtDPa1","11":":police_car_light::police_car_light::police_car_light: Madrid proh\u00edbe la celebraci\u00f3n de las campanadas en la Puerta del Sol y desvela que s\u00ed habr\u00e1 cabalgatas de Reyes Magos https:\/\/t.co\/alUJoZ7Yjg","12":":eyes: \u00a1\u00a1As\u00ed est\u00e1 el r\u00e1nking de los 48 lugares de Espa\u00f1a declarados Patrimonio de la Humanidad!!\n\n:keycap_digit_one: @turgranada \n:keycap_digit_two: @turismocba \n:keycap_digit_three: @Segoviaturismo\n:keycap_digit_four: @toledoturismo\n:keycap_digit_five: @VisitTenerifeES\n\n \u00a1\u00a1Vota el m\u00e1s bello para ti!! :national_park::rainbow:  \nhttps:\/\/t.co\/zZtboBNExB","13":":desktop_computer: @RafaelNadal en #ElHormiguero: la ansiedad, qu\u00e9 cambiar\u00eda de Espa\u00f1a, las fiestas y el tequila... https:\/\/t.co\/rgsFSHxIi7","14":":bomb: Jes\u00e9 entra en directo en #LaCasaFuerte con Jorge Javier: \"Estoy muy enamorado de Aurah\" https:\/\/t.co\/0gPD8HVQl6"},"user_verified":{"0":false,"1":false,"2":false,"3":false,"4":false,"5":false,"6":false,"7":false,"8":false,"9":false,"10":false,"11":false,"12":false,"13":false,"14":false},"created_at":{"0":"2020-12-04 23:47:43","1":"2020-12-04 18:48:21","2":"2020-12-04 14:06:13","3":"2020-12-04 13:50:21","4":"2020-12-04 13:41:16","5":"2020-12-04 13:27:10","6":"2020-12-04 13:20:28","7":"2020-12-04 13:18:48","8":"2020-12-04 13:06:28","9":"2020-12-04 12:43:56","10":"2020-12-04 12:33:28","11":"2020-12-04 10:57:21","12":"2020-12-04 09:07:51","13":"2020-12-04 07:31:09","14":"2020-12-04 07:25:50"},"retweet_count":{"0":8,"1":3,"2":0,"3":4,"4":0,"5":8,"6":12,"7":0,"8":0,"9":10,"10":7,"11":11,"12":4,"13":6,"14":3},"favorite_count":{"0":34,"1":15,"2":0,"3":34,"4":0,"5":34,"6":29,"7":1,"8":0,"9":42,"10":17,"11":37,"12":24,"13":39,"14":23},"user_location":{"0":"Madrid","1":"Madrid","2":"Madrid","3":"Madrid","4":"Madrid","5":"Madrid","6":"Madrid","7":"Madrid","8":"Madrid","9":"Madrid","10":"Madrid","11":"Madrid","12":"Madrid","13":"Madrid","14":"Madrid"},"user_url":{"0":"https:\/\/t.co\/125RuutmjE","1":"https:\/\/t.co\/125RuutmjE","2":"https:\/\/t.co\/125RuutmjE","3":"https:\/\/t.co\/125RuutmjE","4":"https:\/\/t.co\/125RuutmjE","5":"https:\/\/t.co\/125RuutmjE","6":"https:\/\/t.co\/125RuutmjE","7":"https:\/\/t.co\/125RuutmjE","8":"https:\/\/t.co\/125RuutmjE","9":"https:\/\/t.co\/125RuutmjE","10":"https:\/\/t.co\/125RuutmjE","11":"https:\/\/t.co\/125RuutmjE","12":"https:\/\/t.co\/125RuutmjE","13":"https:\/\/t.co\/125RuutmjE","14":"https:\/\/t.co\/125RuutmjE"},"entities":{"0":{"hashtags":[],"symbols":[],"user_mentions":[],"urls":[{"url":"https:\/\/t.co\/TRRZU430Do","expanded_url":"https:\/\/www.marca.com\/tiramillas\/actualidad\/2020\/12\/04\/5fca96c846163f29a28b45d2.html","display_url":"marca.com\/tiramillas\/act\u2026","indices":[69,92]}]},"1":{"hashtags":[],"symbols":[],"user_mentions":[],"urls":[{"url":"https:\/\/t.co\/MCGm0rq0uJ","expanded_url":"https:\/\/www.marca.com\/tiramillas\/actualidad\/2020\/12\/04\/5fca7478e2704e0bb38b4615.html","display_url":"marca.com\/tiramillas\/act\u2026","indices":[75,98]}]},"2":{"hashtags":[],"symbols":[],"user_mentions":[],"urls":[{"url":"https:\/\/t.co\/26EkOUHXEg","expanded_url":"https:\/\/www.marca.com\/tiramillas\/actualidad\/2020\/12\/04\/5fca4191268e3ed3348b45d3.html","display_url":"marca.com\/tiramillas\/act\u2026","indices":[126,149]}]},"3":{"hashtags":[],"symbols":[],"user_mentions":[{"screen_name":"PilarRubio_","name":"Pilar Rubio","id":277554242,"id_str":"277554242","indices":[18,30]}],"urls":[{"url":"https:\/\/t.co\/aTiV0U3SnE","expanded_url":"https:\/\/www.marca.com\/tiramillas\/actualidad\/2020\/12\/04\/5fca3bedca474164508b45bd.html","display_url":"marca.com\/tiramillas\/act\u2026","indices":[76,99]}]},"4":{"hashtags":[],"symbols":[],"user_mentions":[],"urls":[{"url":"https:\/\/t.co\/B97U8NgpbI","expanded_url":"https:\/\/www.marca.com\/tiramillas\/cine-tv\/2020\/12\/04\/5fca3a33268e3e19198b4619.html","display_url":"marca.com\/tiramillas\/cin\u2026","indices":[130,153]}]},"5":{"hashtags":[],"symbols":[],"user_mentions":[],"urls":[{"url":"https:\/\/t.co\/5tz3utcydo","expanded_url":"https:\/\/www.marca.com\/tiramillas\/actualidad\/2020\/12\/03\/5fc8b77ce2704e38688b462b.html","display_url":"marca.com\/tiramillas\/act\u2026","indices":[102,125]}]},"6":{"hashtags":[],"symbols":[],"user_mentions":[],"urls":[{"url":"https:\/\/t.co\/Q3tGkvkxJW","expanded_url":"https:\/\/www.marca.com\/tiramillas\/actualidad\/2020\/12\/04\/5fc9f5b222601def3e8b459b.html","display_url":"marca.com\/tiramillas\/act\u2026","indices":[112,135]}]},"7":{"hashtags":[],"symbols":[],"user_mentions":[],"urls":[{"url":"https:\/\/t.co\/LKF5HwBoA2","expanded_url":"https:\/\/www.marca.com\/tiramillas\/actualidad\/2020\/12\/04\/5fca0475ca474165778b45e4.html","display_url":"marca.com\/tiramillas\/act\u2026","indices":[79,102]}]},"8":{"hashtags":[],"symbols":[],"user_mentions":[],"urls":[{"url":"https:\/\/t.co\/JCMhBcAFJt","expanded_url":"https:\/\/www.marca.com\/tiramillas\/actualidad\/2020\/12\/04\/5fc9d866e2704e15b88b45e0.html","display_url":"marca.com\/tiramillas\/act\u2026","indices":[113,136]}]},"9":{"hashtags":[],"symbols":[],"user_mentions":[{"screen_name":"J_Fdez_Borrell","name":"Javier Fern\u00e1ndez Borrell","id":1297245404380237824,"id_str":"1297245404380237824","indices":[121,136]}],"urls":[{"url":"https:\/\/t.co\/PtNgdIdDRs","expanded_url":"https:\/\/www.marca.com\/tiramillas\/television\/opinion\/2020\/12\/04\/5fca1dc222601d6e548b45b6.html","display_url":"marca.com\/tiramillas\/tel\u2026","indices":[83,106]}]},"10":{"hashtags":[],"symbols":[],"user_mentions":[],"urls":[{"url":"https:\/\/t.co\/LvNTdtDPa1","expanded_url":"https:\/\/www.marca.com\/tiramillas\/television\/2020\/12\/04\/5fca0f0422601d11248b460c.html","display_url":"marca.com\/tiramillas\/tel\u2026","indices":[102,125]}]},"11":{"hashtags":[],"symbols":[],"user_mentions":[],"urls":[{"url":"https:\/\/t.co\/alUJoZ7Yjg","expanded_url":"https:\/\/www.marca.com\/tiramillas\/actualidad\/2020\/12\/04\/5fca056822601def3e8b45a4.html","display_url":"marca.com\/tiramillas\/act\u2026","indices":[122,145]}]},"12":{"hashtags":[],"symbols":[],"user_mentions":[{"screen_name":"turgranada","name":"Turismo Granada","id":300488077,"id_str":"300488077","indices":[96,107]},{"screen_name":"turismocba","name":"C\u00f3rdoba Turismo","id":223862618,"id_str":"223862618","indices":[112,123]},{"screen_name":"Segoviaturismo","name":"Prodestur Segovia Turismo","id":137447831,"id_str":"137447831","indices":[128,143]},{"screen_name":"toledoturismo","name":"Toledo Turismo","id":332857154,"id_str":"332857154","indices":[147,161]},{"screen_name":"VisitTenerifeES","name":"VisitTenerifeES","id":188507582,"id_str":"188507582","indices":[165,181]}],"urls":[{"url":"https:\/\/t.co\/zZtboBNExB","expanded_url":"https:\/\/www.marca.com\/tiramillas\/lujo\/2020\/12\/03\/5fc8db6822601d7f658b4667.html","display_url":"marca.com\/tiramillas\/luj\u2026","indices":[219,242]}]},"13":{"hashtags":[{"text":"ElHormiguero","indices":[18,31]}],"symbols":[],"user_mentions":[{"screen_name":"RafaelNadal","name":"Rafa Nadal","id":344634424,"id_str":"344634424","indices":[2,14]}],"urls":[{"url":"https:\/\/t.co\/rgsFSHxIi7","expanded_url":"https:\/\/www.marca.com\/tenis\/2020\/12\/03\/5fc944ffe2704efd2e8b4573.html","display_url":"marca.com\/tenis\/2020\/12\/\u2026","indices":[99,122]}]},"14":{"hashtags":[{"text":"LaCasaFuerte","indices":[27,40]}],"symbols":[],"user_mentions":[],"urls":[{"url":"https:\/\/t.co\/0gPD8HVQl6","expanded_url":"https:\/\/www.marca.com\/tiramillas\/television\/2020\/12\/04\/5fc97112268e3e84218b45b0.html","display_url":"marca.com\/tiramillas\/tel\u2026","indices":[90,113]}]}}}