{"screen_name":{"0":"diariomedico","1":"diariomedico","2":"diariomedico","3":"diariomedico","4":"diariomedico","5":"diariomedico","6":"diariomedico","7":"diariomedico","8":"diariomedico","9":"diariomedico","10":"diariomedico","11":"diariomedico","12":"diariomedico","13":"diariomedico","14":"diariomedico","15":"diariomedico"},"tweet_id":{"0":1323034592090165252,"1":1323022103176728577,"2":1323006959734448133,"3":1322991832016556033,"4":1322976796615299072,"5":1322961728376840195,"6":1322946805701726213,"7":1322931484173488130,"8":1322916383202705415,"9":1322886131483029504,"10":1322871152671367168,"11":1322855972193402887,"12":1322840829724164101,"13":1322825843450761220,"14":1322810633310642176,"15":1322805358914686976},"is_retweet":{"0":false,"1":false,"2":false,"3":false,"4":false,"5":false,"6":false,"7":false,"8":false,"9":false,"10":false,"11":false,"12":false,"13":false,"14":false,"15":false},"text":{"0":"#Opini\u00f3n | \u00bfLo has le\u00eddo?  \"Protejamos el Estado de Derecho de la covid-19\", dice Federico de Montalvo J\u00e4\u00e4skel\u00e4inen, profesor de Derecho Constitucional de la Universidad de Comillas (Icade)https:\/\/t.co\/g0Aav0CUJl https:\/\/t.co\/2hN3zRAhUf","1":"\"Lo esencial es que las personas no se infecten. Eso es Salud P\u00fablica, concepto distinto a Sanidad P\u00fablica. En pandemias de este tipo se necesita un plan potente de Salud P\u00fablica\" https:\/\/t.co\/T9frZCIu5U Entrevista a @juliomayol https:\/\/t.co\/qX3aydpP8Z","2":"\u00bfLo has le\u00eddo? \u00bfEs posible optimizar los anti-TNF en el combate contra la enfermedad inflamatoria intestinal? https:\/\/t.co\/L7o7dwqz59 https:\/\/t.co\/p2ZzBhl0Pv","3":"#LaConsultaDM | \u00bfHay deber de informar de los riesgos en una cirug\u00eda urgente? https:\/\/t.co\/tfZ1BQrJ5x https:\/\/t.co\/62TVJT1ZlO","4":"#COVID19 | \u00bfLo has le\u00eddo? Recuperar la actividad bajo la sombra cov\u00eddica. https:\/\/t.co\/nSswhI6oTT https:\/\/t.co\/SFNrkWMZ1X","5":"#COVID19 | Las c\u00e9lulas madre mesenquimales activadas con radiaci\u00f3n podr\u00edan ser una potencial v\u00eda de abordaje para la sepsis y neumon\u00eda de pacientes con covid-19 graves, seg\u00fan publica @CellCellPress . El trabajo es de la @CanalUGR https:\/\/t.co\/A0jTMGNNUS Informa @alilo1920 https:\/\/t.co\/Hib4VqmA9v","6":"La integraci\u00f3n de 'big data' de origen biol\u00f3gico y no-biol\u00f3gico es una estrategia creciente en especialidades como la oncolog\u00eda, con el objetivo de lograr una prevenci\u00f3n y\/o tratamiento de precisi\u00f3n, seg\u00fan explica N\u00faria Malats, del @CNIOStopCancer. https:\/\/t.co\/9nfq174tuy https:\/\/t.co\/J19zPKNi6J","7":"#LaConsultaDM | \u00bfC\u00f3mo puede participar un aut\u00f3nomo en un proceso contra la cl\u00ednica donde trabaja? https:\/\/t.co\/alz3Espvq6 https:\/\/t.co\/E7C8Sd76WB","8":"Improvisaci\u00f3n, generalizaci\u00f3n y ruido pol\u00edtico est\u00e9ril https:\/\/t.co\/7671CECcpH Lee la \u00faltima columna de @carmenfefe https:\/\/t.co\/jfyEOTZh2w","9":"La relaci\u00f3n entre Dermatolog\u00eda Est\u00e9tica y cosm\u00e9tica se traduce en productos que potencian y protegen los resultados de los tratamientos m\u00e9dicos https:\/\/t.co\/432lRJXRRR https:\/\/t.co\/WH5XqoV1i7","10":"#Admirables | Durante esta pandemia, la directora de Enfermer\u00eda del Hospital Covid-19 Ifema, Ver\u00f3nica Real, ha podido objetivar que sin los cuidados enfermeros no hay ni recuperaci\u00f3n ni mejora de la salud. https:\/\/t.co\/Wh1L4TOCaq Por @aserranogomez https:\/\/t.co\/tsZiwO4rfg","11":"Tribuna de Anna Riera, directora de participaci\u00f3n asociativa de la Uni\u00f3n Catalana de Hospitales ( @uchcat ) : Transformando la prestaci\u00f3n de servicios y accesibilidad m\u00e1s all\u00e1 de la covid. https:\/\/t.co\/ZaMqmVEPMG https:\/\/t.co\/ZbDJjz2ZX9","12":"Jos\u00e9 Antonio Guti\u00e9rrez Fuentes, director de la Fundaci\u00f3n GADEA @gadeaciencia critica la falta de apoyos desde Espa\u00f1a para que Francisco Mojica luchara por el Nobel. https:\/\/t.co\/i1YjbhpWqK https:\/\/t.co\/0yYxtu3YIW","13":"#laboral I \"Veo dif\u00edcil que los m\u00e9dicos logremos algo sin un enfrentamiento muy fuerte\" #Entrevista a Andr\u00e9s C\u00e1novas, expresidente de @cesm_sindicatos y exsecretario general de @CESM_CV @TomasToranzo1 @victorpedrera https:\/\/t.co\/KlOkGROTjV https:\/\/t.co\/NZ3y0BhaBF","14":"La #COVID19 no va a retrasar los plazos de la I+D de @BoehringerES, seg\u00fan nos cuenta su director m\u00e9dico Ren\u00e9 Saito https:\/\/t.co\/RG0AOt2zY6 https:\/\/t.co\/gUOI8PfktC","15":"#COVID19 | La vacuna pedi\u00e1trica DTP podr\u00eda proteger del SARS-CoV-2 mediante inmunidad cruzada, seg\u00fan un estudio que publica @FrontImmunol y realizado en la @unicomplutense https:\/\/t.co\/p9r3rd2tb8 Por @alilo1920 https:\/\/t.co\/I76qfO9dqD"},"user_verified":{"0":false,"1":false,"2":false,"3":false,"4":false,"5":false,"6":false,"7":false,"8":false,"9":false,"10":false,"11":false,"12":false,"13":false,"14":false,"15":false},"created_at":{"0":"2020-11-01 22:50:02","1":"2020-11-01 22:00:24","2":"2020-11-01 21:00:14","3":"2020-11-01 20:00:07","4":"2020-11-01 19:00:22","5":"2020-11-01 18:00:30","6":"2020-11-01 17:01:12","7":"2020-11-01 16:00:19","8":"2020-11-01 15:00:19","9":"2020-11-01 13:00:06","10":"2020-11-01 12:00:35","11":"2020-11-01 11:00:15","12":"2020-11-01 10:00:05","13":"2020-11-01 09:00:32","14":"2020-11-01 08:00:06","15":"2020-11-01 07:39:08"},"retweet_count":{"0":0,"1":5,"2":0,"3":0,"4":0,"5":1,"6":0,"7":0,"8":1,"9":0,"10":1,"11":0,"12":0,"13":2,"14":2,"15":12},"favorite_count":{"0":0,"1":15,"2":1,"3":1,"4":0,"5":4,"6":1,"7":0,"8":0,"9":2,"10":4,"11":2,"12":3,"13":7,"14":4,"15":11},"user_location":{"0":"Madrid","1":"Madrid","2":"Madrid","3":"Madrid","4":"Madrid","5":"Madrid","6":"Madrid","7":"Madrid","8":"Madrid","9":"Madrid","10":"Madrid","11":"Madrid","12":"Madrid","13":"Madrid","14":"Madrid","15":"Madrid"},"user_url":{"0":"http:\/\/t.co\/9yU5u7xTRr","1":"http:\/\/t.co\/9yU5u7xTRr","2":"http:\/\/t.co\/9yU5u7xTRr","3":"http:\/\/t.co\/9yU5u7xTRr","4":"http:\/\/t.co\/9yU5u7xTRr","5":"http:\/\/t.co\/9yU5u7xTRr","6":"http:\/\/t.co\/9yU5u7xTRr","7":"http:\/\/t.co\/9yU5u7xTRr","8":"http:\/\/t.co\/9yU5u7xTRr","9":"http:\/\/t.co\/9yU5u7xTRr","10":"http:\/\/t.co\/9yU5u7xTRr","11":"http:\/\/t.co\/9yU5u7xTRr","12":"http:\/\/t.co\/9yU5u7xTRr","13":"http:\/\/t.co\/9yU5u7xTRr","14":"http:\/\/t.co\/9yU5u7xTRr","15":"http:\/\/t.co\/9yU5u7xTRr"},"entities":{"0":{"hashtags":[{"text":"Opini\u00f3n","indices":[0,8]}],"symbols":[],"user_mentions":[],"urls":[{"url":"https:\/\/t.co\/g0Aav0CUJl","expanded_url":"https:\/\/bit.ly\/31Humhy","display_url":"bit.ly\/31Humhy","indices":[189,212]}],"media":[{"id":1323034590848733186,"id_str":"1323034590848733186","indices":[213,236],"media_url":"http:\/\/pbs.twimg.com\/media\/Elxc810X0AIXTVx.jpg","media_url_https":"https:\/\/pbs.twimg.com\/media\/Elxc810X0AIXTVx.jpg","url":"https:\/\/t.co\/2hN3zRAhUf","display_url":"pic.twitter.com\/2hN3zRAhUf","expanded_url":"https:\/\/twitter.com\/diariomedico\/status\/1323034592090165252\/photo\/1","type":"photo","sizes":{"thumb":{"w":150,"h":150,"resize":"crop"},"large":{"w":300,"h":300,"resize":"fit"},"medium":{"w":300,"h":300,"resize":"fit"},"small":{"w":300,"h":300,"resize":"fit"}}}]},"1":{"hashtags":[],"symbols":[],"user_mentions":[{"screen_name":"juliomayol","name":"Julio Mayol","id":28655732,"id_str":"28655732","indices":[217,228]}],"urls":[{"url":"https:\/\/t.co\/T9frZCIu5U","expanded_url":"https:\/\/bit.ly\/35uFQps","display_url":"bit.ly\/35uFQps","indices":[180,203]}],"media":[{"id":1323022101515771904,"id_str":"1323022101515771904","indices":[229,252],"media_url":"http:\/\/pbs.twimg.com\/media\/ElxRl3bWoAAOc1P.jpg","media_url_https":"https:\/\/pbs.twimg.com\/media\/ElxRl3bWoAAOc1P.jpg","url":"https:\/\/t.co\/qX3aydpP8Z","display_url":"pic.twitter.com\/qX3aydpP8Z","expanded_url":"https:\/\/twitter.com\/diariomedico\/status\/1323022103176728577\/photo\/1","type":"photo","sizes":{"thumb":{"w":150,"h":150,"resize":"crop"},"small":{"w":680,"h":453,"resize":"fit"},"large":{"w":1200,"h":800,"resize":"fit"},"medium":{"w":1200,"h":800,"resize":"fit"}}}]},"2":{"hashtags":[],"symbols":[],"user_mentions":[],"urls":[{"url":"https:\/\/t.co\/L7o7dwqz59","expanded_url":"https:\/\/bit.ly\/2TIgGy8","display_url":"bit.ly\/2TIgGy8","indices":[110,133]}],"media":[{"id":1323006957842817024,"id_str":"1323006957842817024","indices":[134,157],"media_url":"http:\/\/pbs.twimg.com\/media\/ElxD0Y2XYAAOMyy.jpg","media_url_https":"https:\/\/pbs.twimg.com\/media\/ElxD0Y2XYAAOMyy.jpg","url":"https:\/\/t.co\/p2ZzBhl0Pv","display_url":"pic.twitter.com\/p2ZzBhl0Pv","expanded_url":"https:\/\/twitter.com\/diariomedico\/status\/1323006959734448133\/photo\/1","type":"photo","sizes":{"large":{"w":1200,"h":800,"resize":"fit"},"thumb":{"w":150,"h":150,"resize":"crop"},"medium":{"w":1200,"h":800,"resize":"fit"},"small":{"w":680,"h":453,"resize":"fit"}}}]},"3":{"hashtags":[{"text":"LaConsultaDM","indices":[0,13]}],"symbols":[],"user_mentions":[],"urls":[{"url":"https:\/\/t.co\/tfZ1BQrJ5x","expanded_url":"https:\/\/bit.ly\/3ejutFa","display_url":"bit.ly\/3ejutFa","indices":[78,101]}],"media":[{"id":1322991830464667649,"id_str":"1322991830464667649","indices":[102,125],"media_url":"http:\/\/pbs.twimg.com\/media\/Elw2D2-XIAEjFB2.jpg","media_url_https":"https:\/\/pbs.twimg.com\/media\/Elw2D2-XIAEjFB2.jpg","url":"https:\/\/t.co\/62TVJT1ZlO","display_url":"pic.twitter.com\/62TVJT1ZlO","expanded_url":"https:\/\/twitter.com\/diariomedico\/status\/1322991832016556033\/photo\/1","type":"photo","sizes":{"small":{"w":680,"h":453,"resize":"fit"},"thumb":{"w":150,"h":150,"resize":"crop"},"large":{"w":1200,"h":800,"resize":"fit"},"medium":{"w":1200,"h":800,"resize":"fit"}}}]},"4":{"hashtags":[{"text":"COVID19","indices":[0,8]}],"symbols":[],"user_mentions":[],"urls":[{"url":"https:\/\/t.co\/nSswhI6oTT","expanded_url":"https:\/\/bit.ly\/3mxLPB5","display_url":"bit.ly\/3mxLPB5","indices":[74,97]}],"media":[{"id":1322976794673324035,"id_str":"1322976794673324035","indices":[98,121],"media_url":"http:\/\/pbs.twimg.com\/media\/ElwoYqSWoAMt1Je.jpg","media_url_https":"https:\/\/pbs.twimg.com\/media\/ElwoYqSWoAMt1Je.jpg","url":"https:\/\/t.co\/SFNrkWMZ1X","display_url":"pic.twitter.com\/SFNrkWMZ1X","expanded_url":"https:\/\/twitter.com\/diariomedico\/status\/1322976796615299072\/photo\/1","type":"photo","sizes":{"thumb":{"w":150,"h":150,"resize":"crop"},"large":{"w":1200,"h":800,"resize":"fit"},"medium":{"w":1200,"h":800,"resize":"fit"},"small":{"w":680,"h":453,"resize":"fit"}}}]},"5":{"hashtags":[{"text":"COVID19","indices":[0,8]}],"symbols":[],"user_mentions":[{"screen_name":"CellCellPress","name":"Cell","id":65134016,"id_str":"65134016","indices":[183,197]},{"screen_name":"CanalUGR","name":"Universidad Granada","id":144804999,"id_str":"144804999","indices":[220,229]},{"screen_name":"alilo1920","name":"RAQUEL SERRANO","id":840646062440345600,"id_str":"840646062440345600","indices":[262,272]}],"urls":[{"url":"https:\/\/t.co\/A0jTMGNNUS","expanded_url":"https:\/\/bit.ly\/3mC2lQg","display_url":"bit.ly\/3mC2lQg","indices":[230,253]}],"media":[{"id":1322961726480986113,"id_str":"1322961726480986113","indices":[273,296],"media_url":"http:\/\/pbs.twimg.com\/media\/Elwark5WMAE-PC4.jpg","media_url_https":"https:\/\/pbs.twimg.com\/media\/Elwark5WMAE-PC4.jpg","url":"https:\/\/t.co\/Hib4VqmA9v","display_url":"pic.twitter.com\/Hib4VqmA9v","expanded_url":"https:\/\/twitter.com\/diariomedico\/status\/1322961728376840195\/photo\/1","type":"photo","sizes":{"small":{"w":680,"h":453,"resize":"fit"},"thumb":{"w":150,"h":150,"resize":"crop"},"large":{"w":1200,"h":800,"resize":"fit"},"medium":{"w":1200,"h":800,"resize":"fit"}}}]},"6":{"hashtags":[],"symbols":[],"user_mentions":[{"screen_name":"CNIOStopCancer","name":"CNIO Stop Cancer","id":374426116,"id_str":"374426116","indices":[232,247]}],"urls":[{"url":"https:\/\/t.co\/9nfq174tuy","expanded_url":"https:\/\/bit.ly\/3218ldz","display_url":"bit.ly\/3218ldz","indices":[249,272]}],"media":[{"id":1322946804099518465,"id_str":"1322946804099518465","indices":[273,296],"media_url":"http:\/\/pbs.twimg.com\/media\/ElwNG-sXEAE2U9o.jpg","media_url_https":"https:\/\/pbs.twimg.com\/media\/ElwNG-sXEAE2U9o.jpg","url":"https:\/\/t.co\/J19zPKNi6J","display_url":"pic.twitter.com\/J19zPKNi6J","expanded_url":"https:\/\/twitter.com\/diariomedico\/status\/1322946805701726213\/photo\/1","type":"photo","sizes":{"large":{"w":1200,"h":800,"resize":"fit"},"thumb":{"w":150,"h":150,"resize":"crop"},"medium":{"w":1200,"h":800,"resize":"fit"},"small":{"w":680,"h":453,"resize":"fit"}}}]},"7":{"hashtags":[{"text":"LaConsultaDM","indices":[0,13]}],"symbols":[],"user_mentions":[],"urls":[{"url":"https:\/\/t.co\/alz3Espvq6","expanded_url":"https:\/\/bit.ly\/37Vu3U9","display_url":"bit.ly\/37Vu3U9","indices":[98,121]}],"media":[{"id":1322931482399264770,"id_str":"1322931482399264770","indices":[122,145],"media_url":"http:\/\/pbs.twimg.com\/media\/Elv_LI6W0AI4J7u.jpg","media_url_https":"https:\/\/pbs.twimg.com\/media\/Elv_LI6W0AI4J7u.jpg","url":"https:\/\/t.co\/E7C8Sd76WB","display_url":"pic.twitter.com\/E7C8Sd76WB","expanded_url":"https:\/\/twitter.com\/diariomedico\/status\/1322931484173488130\/photo\/1","type":"photo","sizes":{"thumb":{"w":150,"h":150,"resize":"crop"},"large":{"w":1200,"h":800,"resize":"fit"},"medium":{"w":1200,"h":800,"resize":"fit"},"small":{"w":680,"h":453,"resize":"fit"}}}]},"8":{"hashtags":[],"symbols":[],"user_mentions":[{"screen_name":"carmenfefe","name":"Carmen Fern\u00e1ndez","id":375713228,"id_str":"375713228","indices":[104,115]}],"urls":[{"url":"https:\/\/t.co\/7671CECcpH","expanded_url":"https:\/\/bit.ly\/2HPQTkY","display_url":"bit.ly\/2HPQTkY","indices":[55,78]}],"media":[{"id":1322916381575229444,"id_str":"1322916381575229444","indices":[116,139],"media_url":"http:\/\/pbs.twimg.com\/media\/ElvxcJ9WMAQI5qd.jpg","media_url_https":"https:\/\/pbs.twimg.com\/media\/ElvxcJ9WMAQI5qd.jpg","url":"https:\/\/t.co\/jfyEOTZh2w","display_url":"pic.twitter.com\/jfyEOTZh2w","expanded_url":"https:\/\/twitter.com\/diariomedico\/status\/1322916383202705415\/photo\/1","type":"photo","sizes":{"thumb":{"w":150,"h":150,"resize":"crop"},"large":{"w":1200,"h":800,"resize":"fit"},"medium":{"w":1200,"h":800,"resize":"fit"},"small":{"w":680,"h":453,"resize":"fit"}}}]},"9":{"hashtags":[],"symbols":[],"user_mentions":[],"urls":[{"url":"https:\/\/t.co\/432lRJXRRR","expanded_url":"https:\/\/bit.ly\/35FCtMv","display_url":"bit.ly\/35FCtMv","indices":[144,167]}],"media":[{"id":1322886129859862531,"id_str":"1322886129859862531","indices":[168,191],"media_url":"http:\/\/pbs.twimg.com\/media\/ElvV7RiWoAMPePD.jpg","media_url_https":"https:\/\/pbs.twimg.com\/media\/ElvV7RiWoAMPePD.jpg","url":"https:\/\/t.co\/WH5XqoV1i7","display_url":"pic.twitter.com\/WH5XqoV1i7","expanded_url":"https:\/\/twitter.com\/diariomedico\/status\/1322886131483029504\/photo\/1","type":"photo","sizes":{"thumb":{"w":150,"h":150,"resize":"crop"},"small":{"w":680,"h":453,"resize":"fit"},"large":{"w":1200,"h":800,"resize":"fit"},"medium":{"w":1200,"h":800,"resize":"fit"}}}]},"10":{"hashtags":[{"text":"Admirables","indices":[0,11]}],"symbols":[],"user_mentions":[{"screen_name":"aserranogomez","name":"Alicia Serrano G\u00f3mez","id":464858825,"id_str":"464858825","indices":[234,248]}],"urls":[{"url":"https:\/\/t.co\/Wh1L4TOCaq","expanded_url":"https:\/\/bit.ly\/3kJhO0B","display_url":"bit.ly\/3kJhO0B","indices":[206,229]}],"media":[{"id":1322871150943346688,"id_str":"1322871150943346688","indices":[249,272],"media_url":"http:\/\/pbs.twimg.com\/media\/ElvITYuXIAA2n8h.jpg","media_url_https":"https:\/\/pbs.twimg.com\/media\/ElvITYuXIAA2n8h.jpg","url":"https:\/\/t.co\/tsZiwO4rfg","display_url":"pic.twitter.com\/tsZiwO4rfg","expanded_url":"https:\/\/twitter.com\/diariomedico\/status\/1322871152671367168\/photo\/1","type":"photo","sizes":{"thumb":{"w":150,"h":150,"resize":"crop"},"large":{"w":1200,"h":800,"resize":"fit"},"medium":{"w":1200,"h":800,"resize":"fit"},"small":{"w":680,"h":453,"resize":"fit"}}}]},"11":{"hashtags":[],"symbols":[],"user_mentions":[{"screen_name":"uchcat","name":"La Uni\u00f3","id":1359101370,"id_str":"1359101370","indices":[98,105]}],"urls":[{"url":"https:\/\/t.co\/ZaMqmVEPMG","expanded_url":"https:\/\/bit.ly\/34Ez4hY","display_url":"bit.ly\/34Ez4hY","indices":[189,212]}],"media":[{"id":1322855970356240384,"id_str":"1322855970356240384","indices":[213,236],"media_url":"http:\/\/pbs.twimg.com\/media\/Elu6fwoWoAAXww8.jpg","media_url_https":"https:\/\/pbs.twimg.com\/media\/Elu6fwoWoAAXww8.jpg","url":"https:\/\/t.co\/ZbDJjz2ZX9","display_url":"pic.twitter.com\/ZbDJjz2ZX9","expanded_url":"https:\/\/twitter.com\/diariomedico\/status\/1322855972193402887\/photo\/1","type":"photo","sizes":{"small":{"w":680,"h":453,"resize":"fit"},"thumb":{"w":150,"h":150,"resize":"crop"},"large":{"w":1200,"h":800,"resize":"fit"},"medium":{"w":1200,"h":800,"resize":"fit"}}}]},"12":{"hashtags":[],"symbols":[],"user_mentions":[{"screen_name":"gadeaciencia","name":"Gadea Ciencia","id":897565915969138689,"id_str":"897565915969138689","indices":[63,76]}],"urls":[{"url":"https:\/\/t.co\/i1YjbhpWqK","expanded_url":"https:\/\/bit.ly\/2TtDEJx","display_url":"bit.ly\/2TtDEJx","indices":[165,188]}],"media":[{"id":1322840828163796992,"id_str":"1322840828163796992","indices":[189,212],"media_url":"http:\/\/pbs.twimg.com\/media\/ElusuXkWMAAPLJw.jpg","media_url_https":"https:\/\/pbs.twimg.com\/media\/ElusuXkWMAAPLJw.jpg","url":"https:\/\/t.co\/0yYxtu3YIW","display_url":"pic.twitter.com\/0yYxtu3YIW","expanded_url":"https:\/\/twitter.com\/diariomedico\/status\/1322840829724164101\/photo\/1","type":"photo","sizes":{"large":{"w":1200,"h":800,"resize":"fit"},"thumb":{"w":150,"h":150,"resize":"crop"},"small":{"w":680,"h":453,"resize":"fit"},"medium":{"w":1200,"h":800,"resize":"fit"}}}]},"13":{"hashtags":[{"text":"laboral","indices":[0,8]},{"text":"Entrevista","indices":[88,99]}],"symbols":[],"user_mentions":[{"screen_name":"cesm_sindicatos","name":"CESM #PonteLaMascarilla","id":2589440382,"id_str":"2589440382","indices":[134,150]},{"screen_name":"CESM_CV","name":"SindicatoMedico_CESM-CV","id":997855009193844737,"id_str":"997855009193844737","indices":[177,185]},{"screen_name":"TomasToranzo1","name":"Tomas Toranzo Cepeda","id":390707379,"id_str":"390707379","indices":[186,200]},{"screen_name":"victorpedrera","name":"V\u00edctor Pedrera Carbonell","id":283690614,"id_str":"283690614","indices":[201,215]}],"urls":[{"url":"https:\/\/t.co\/KlOkGROTjV","expanded_url":"https:\/\/bit.ly\/35RZP1C","display_url":"bit.ly\/35RZP1C","indices":[216,239]}],"media":[{"id":1322825842066677760,"id_str":"1322825842066677760","indices":[240,263],"media_url":"http:\/\/pbs.twimg.com\/media\/ElufGEAXYAAL3aU.jpg","media_url_https":"https:\/\/pbs.twimg.com\/media\/ElufGEAXYAAL3aU.jpg","url":"https:\/\/t.co\/NZ3y0BhaBF","display_url":"pic.twitter.com\/NZ3y0BhaBF","expanded_url":"https:\/\/twitter.com\/diariomedico\/status\/1322825843450761220\/photo\/1","type":"photo","sizes":{"thumb":{"w":150,"h":150,"resize":"crop"},"small":{"w":408,"h":680,"resize":"fit"},"medium":{"w":600,"h":1000,"resize":"fit"},"large":{"w":600,"h":1000,"resize":"fit"}}}]},"14":{"hashtags":[{"text":"COVID19","indices":[3,11]}],"symbols":[],"user_mentions":[{"screen_name":"BoehringerES","name":"Boehringer Espa\u00f1a","id":228751678,"id_str":"228751678","indices":[53,66]}],"urls":[{"url":"https:\/\/t.co\/RG0AOt2zY6","expanded_url":"https:\/\/bit.ly\/2HuVxoZ","display_url":"bit.ly\/2HuVxoZ","indices":[115,138]}],"media":[{"id":1322810631813275648,"id_str":"1322810631813275648","indices":[139,162],"media_url":"http:\/\/pbs.twimg.com\/media\/EluRQtZXIAA7Zzs.jpg","media_url_https":"https:\/\/pbs.twimg.com\/media\/EluRQtZXIAA7Zzs.jpg","url":"https:\/\/t.co\/gUOI8PfktC","display_url":"pic.twitter.com\/gUOI8PfktC","expanded_url":"https:\/\/twitter.com\/diariomedico\/status\/1322810633310642176\/photo\/1","type":"photo","sizes":{"small":{"w":680,"h":453,"resize":"fit"},"thumb":{"w":150,"h":150,"resize":"crop"},"medium":{"w":1200,"h":800,"resize":"fit"},"large":{"w":1200,"h":800,"resize":"fit"}}}]},"15":{"hashtags":[{"text":"COVID19","indices":[0,8]}],"symbols":[],"user_mentions":[{"screen_name":"FrontImmunol","name":"Frontiers Immunology","id":397381576,"id_str":"397381576","indices":[124,137]},{"screen_name":"unicomplutense","name":"Complutense","id":85343435,"id_str":"85343435","indices":[156,171]},{"screen_name":"alilo1920","name":"RAQUEL SERRANO","id":840646062440345600,"id_str":"840646062440345600","indices":[200,210]}],"urls":[{"url":"https:\/\/t.co\/p9r3rd2tb8","expanded_url":"https:\/\/bit.ly\/35TmGtI","display_url":"bit.ly\/35TmGtI","indices":[172,195]}],"media":[{"id":1322805357534679040,"id_str":"1322805357534679040","indices":[211,234],"media_url":"http:\/\/pbs.twimg.com\/media\/EluMdtLWkAAk6oB.jpg","media_url_https":"https:\/\/pbs.twimg.com\/media\/EluMdtLWkAAk6oB.jpg","url":"https:\/\/t.co\/I76qfO9dqD","display_url":"pic.twitter.com\/I76qfO9dqD","expanded_url":"https:\/\/twitter.com\/diariomedico\/status\/1322805358914686976\/photo\/1","type":"photo","sizes":{"thumb":{"w":150,"h":150,"resize":"crop"},"large":{"w":1200,"h":800,"resize":"fit"},"small":{"w":680,"h":453,"resize":"fit"},"medium":{"w":1200,"h":800,"resize":"fit"}}}]}}}