{"screen_name":{"0":"diariomedico","1":"diariomedico","2":"diariomedico","3":"diariomedico","4":"diariomedico","5":"diariomedico","6":"diariomedico","7":"diariomedico","8":"diariomedico","9":"diariomedico","10":"diariomedico","11":"diariomedico","12":"diariomedico","13":"diariomedico","14":"diariomedico","15":"diariomedico","16":"diariomedico","17":"diariomedico","18":"diariomedico","19":"diariomedico","20":"diariomedico","21":"diariomedico","22":"diariomedico","23":"diariomedico","24":"diariomedico","25":"diariomedico","26":"diariomedico","27":"diariomedico","28":"diariomedico","29":"diariomedico","30":"diariomedico","31":"diariomedico","32":"diariomedico","33":"diariomedico"},"tweet_id":{"0":1323759371898290178,"1":1323744271309164546,"2":1323729170392899586,"3":1323721897205530624,"4":1323721165471391744,"5":1323720627170217985,"6":1323718736675774466,"7":1323717907537403907,"8":1323717128311156743,"9":1323716447143690242,"10":1323714498864287748,"11":1323714091836493831,"12":1323713648565620741,"13":1323712839710838785,"14":1323711843538472960,"15":1323708872767508480,"16":1323707835772010496,"17":1323706124223324172,"18":1323705714225930240,"19":1323704653268328448,"20":1323699831257399299,"21":1323698971953549314,"22":1323668783257526273,"23":1323653674279854081,"24":1323638572033937408,"25":1323623473835630593,"26":1323608399607701510,"27":1323593272812515328,"28":1323578178552647680,"29":1323563083864920065,"30":1323547978318176257,"31":1323532879448735744,"32":1323517777181888513,"33":1323505343817748485},"is_retweet":{"0":false,"1":false,"2":false,"3":false,"4":false,"5":false,"6":false,"7":false,"8":false,"9":false,"10":false,"11":false,"12":false,"13":false,"14":false,"15":false,"16":false,"17":false,"18":false,"19":false,"20":false,"21":false,"22":false,"23":false,"24":false,"25":false,"26":false,"27":false,"28":false,"29":false,"30":false,"31":false,"32":false,"33":false},"text":{"0":"#Empresas | La compa\u00f1\u00eda americana Vedere Bio, recien adquirida por @Novartis, posee una plataforma de terapias g\u00e9nicas basadas en virus adenoasociados y un programa de optogen\u00e9tica para la p\u00e9rdida de visi\u00f3n https:\/\/t.co\/3kwiRVSx4I https:\/\/t.co\/HG0jBLwe1c","1":"#COVID19 I @amytsmedicos asegura que la obra del futuro hospital Isabel Zendal sigue a pleno ritmo, pese a lo que diga @SaludMadrid Por @frangoiri @jezquerra57 @eruizescudero @SheilajustoS @tki_ojo @TomasToranzo1 @cesm_sindicatos @mlalanda https:\/\/t.co\/t9UCCNAdSo https:\/\/t.co\/WXCyp8PT1I","2":"La Audiencia Provincial de A Coru\u00f1a ha anulado el testamento de una anciana ingresada en una residencia por considerar que, a pesar de no estar incapacitada judicialmente cuando lo firm\u00f3, ten\u00eda \u201cgravemente afectada su capacidad mental\u201d. https:\/\/t.co\/kOR2ITux00 https:\/\/t.co\/tZDCTqOhMq","3":"#Admirables |  @SromeroOmc    \"Hay que tomar medidas, no podemos llegar tarde otra vez. Nos toca que la pandemia se aborde desde una visi\u00f3n social, el enfoque cl\u00ednico no es suficiente. Y apelar a la responsabilidad de cada uno\"","4":"#Admirables | @SromeroOmc  \"Nos toca seguir trabajando y estamos en una situaci\u00f3n muy complicada, ahora m\u00e1s q nunca tenemos la obligaci\u00f3n de asumir riesgos\"","5":"#Admirables | Las primeras palabras de @SromeroOmc  presidente de @omc_espana son en recuerdo a los sanitarios fallecidos durante la pandemia y a los que actualmente est\u00e1n luchando contra el virus. https:\/\/t.co\/5CbQmhOZay","6":"#Admirables | \"Los farmac\u00e9uticos espa\u00f1oles tenemos capacitaci\u00f3n t\u00e9cnica, cient\u00edfica y sanitaria.Hemos instaurado las medidas adoptadas en la pandemia para el abastecimiento, la de f\u00e1rmacos a poblaci\u00f3n vulnerable, as\u00ed como la coordinaci\u00f3n entre farmacia hospitalaria y comunitaria\" https:\/\/t.co\/ZefIeQAJ1F","7":"#Admirables | Jes\u00fas Aguilar @PresidenteCGCOF presidente del Consejo General de Colegios @Farmaceuticos_ : \"Nuestro m\u00e1ximo reconocimiento a las v\u00edctimas de esta pandemia y a sus familiares, especialmente a los 21 profesionales de la farmacia\" https:\/\/t.co\/pLnEqeZ1Ed","8":"#Admirables | Mar\u00eda R\u00edo, vicepresidenta y directora de @GileadSciences  todo el sector sanitario ha tenido un comportamiento de 10 durante toda la pandemia","9":"#Admirables | Diego Ayuso, Secretario General del @CGEnfermeria agradece a todos los profesionales sanitaros que han dado el 300%  trabajando en equipo y a todas las enfermeras que se juegan la vida y est\u00e1n al lado de los pacientes. https:\/\/t.co\/H2r4S344eT","10":"#Admirables | El presidente de @BidaFarma Antonio P\u00e9rez Ostos agradece por v\u00eddeo a todos los farmac\u00e9uticos y al sector de la distribuci\u00f3n su labor durante la pandemia.","11":"#MedSafetyWeek | @AEMPSGOB impulsa la notificaci\u00f3n de sospechas de reacciones adversas a #medicamentos. Te lo contamos aqu\u00ed: https:\/\/t.co\/KZAvV3nWUN https:\/\/t.co\/LDYaMRauHu","12":"#Admirables | \"Es el momento de dejar los egos a un lado y trabajar codo con codo\", @magomore https:\/\/t.co\/ESTv0BlhUx","13":"Un toque de humor con @magomore en el acto de reconocimiento a los sanitarios #Admirables. \"Dejemos de quejarnos, empecemos a ver algo positivo en esto que estamos viviendo\" https:\/\/t.co\/MeFO8QmdGi","14":"Actuaci\u00f3n del @magomore en el acto #Admirables. Explica c\u00f3mo gestionar el estr\u00e9s y la frustraci\u00f3n.  \"Lo que hay es lo que hay\" https:\/\/t.co\/saZRuufN7L","15":"Han sido momentos muy duros para los sanitarios y los periodistas, que os hemos acompa\u00f1ado en esta pandemia con jornadas maratonianas. Nos toca a los MMCC rendir ese homenaje a los sanitarios. Esta tarde cerramos el c\u00edrculo con el homenaje #admirables. https:\/\/t.co\/Zwq9daydBL","16":"#Admirables | Recuerdos de @miguelgcorral para los sanitarios fallecidos en la pandemia: \"La salud lo es todo\" https:\/\/t.co\/krwubs98cq","17":"#Admirables | Antonio Fern\u00e1ndez Galiano, presidente de @unidadeditorial enumera las lecciones que aprender de esta pandemia: 1. Necesitamos una mayor integraci\u00f3n entre sanidad p\u00fablica y privada. 2. Gesti\u00f3n eficaz 3. Reforzar la sanidad https:\/\/t.co\/AxkbRq4iIB","18":"#COVID19 | Los datos no mejoran: doce comunidades con una incidencia acumulada superior a 500 https:\/\/t.co\/LTAsYOSd2v https:\/\/t.co\/L41nlWJE5q","19":"#Admirables | Comienza el acto con @miguelgcorral  Director del \u00c1rea de Salud de @unidadeditorial agradeciendo a los sanitarios su labor. https:\/\/t.co\/XXAUncWFpJ","20":"Todo preparado, en breve comenzamos https:\/\/t.co\/WWN9mVlZMk","21":"#COVID19 | El informe publicado este lunes por el Ministerio de Sanidad revela 55.019 nuevos casos confirmados desde el viernes, unos 18.340 diarios. Los fallecimientos se elevan a 379 https:\/\/t.co\/RVdjGmEBA8 https:\/\/t.co\/oHxTAFgden","22":"\"\"El #estadodealarmaesp no permite confinamientos domiciliarios, ni cierres perimetrales inferiores a 7 d\u00edas\", dice Josefa Cantero, presidenta de @sespas, en una entrevista con @saldeana  https:\/\/t.co\/U7FgF6tcwH https:\/\/t.co\/FtixX2aYfj","23":"#COVID19 | @salvadorilla no cede a la petici\u00f3n de permitir confinamientos domiciliarios y pide a @GobAsturias que d\u00e9 tiempo para ver los resultados de las medidas actuales  https:\/\/t.co\/idbUTVDqvL https:\/\/t.co\/wdAFS9TU9r","24":".@IdiazAyuso, presidenta de @ComunidadMadrid, anuncia que pedir\u00e1 a la @AEMPSGOB autorizaci\u00f3n para que las farmacias realicen test de ant\u00edgenos #COVID19, como ya reclam\u00f3 Luis Gonz\u00e1lez @COFMadrid https:\/\/t.co\/eRnS0gbMC9 https:\/\/t.co\/6AIGhCtZ67","25":"#LABCLIN2020 | \"La realidad del laboratorio cl\u00ednico va mucho m\u00e1s all\u00e1 de la #COVID19\" @congresolabclin Lo cuenta @yoyobustelo aqu\u00ed: https:\/\/t.co\/f4NgTh5siN https:\/\/t.co\/erpTSxXLKG","26":"El nivel de az\u00facar en sangre predice el pron\u00f3stico en #COVID19, seg\u00fan un estudio de @Sociedad_SEMI. Te lo contamos. https:\/\/t.co\/dTUasfdGw6 https:\/\/t.co\/OWGKHQP5oV","27":"Ram\u00f3n Garc\u00eda Sanz, presidente de la @sehh_es, considera que deber\u00edan designarse m\u00e1s centros para realizar la terapia con #CAR-T en previsi\u00f3n a que crezcan sus indicaciones. https:\/\/t.co\/nVk0oKkHo7 https:\/\/t.co\/3fXjTaNmJL","28":"La espa\u00f1ola @AshoOficial consigue su primer contrato internacional https:\/\/t.co\/3Zew8zAZOb https:\/\/t.co\/NLNNSbXZWQ","29":"Un v\u00eddeo resume la cirug\u00eda para la #atresia esof\u00e1gica que desarrollan en el Hospital Gregorio Mara\u00f1\u00f3n https:\/\/t.co\/dujTwiPvpo https:\/\/t.co\/kQOzS8mgRw","30":"#Admirables | Mar\u00eda Cruz Delgado, presidenta de @Fepimcti : \u201cNo podemos permitir que los pacientes con #COVID19 est\u00e9n solos\u201d  https:\/\/t.co\/huUTSJ3yoI https:\/\/t.co\/Liks6uuvFY","31":"#LaConsultaDM | \u00bfHay deber de informar de los riesgos en una cirug\u00eda urgente? https:\/\/t.co\/tfZ1BQrJ5x https:\/\/t.co\/ZG72uyTacD","32":"#Admirables | \u00bfLo has le\u00eddo? Durante esta pandemia, la directora de Enfermer\u00eda del Hospital Covid-19 Ifema, Ver\u00f3nica Real, ha podido objetivar que sin los cuidados enfermeros no hay ni recuperaci\u00f3n ni mejora de la salud. https:\/\/t.co\/Wh1L4TOCaq Por @aserranogomez https:\/\/t.co\/D5rW643z3q","33":"Auge y ca\u00edda de la cloroquina. Fue el f\u00e1rmaco m\u00e1s utilizado y 'politizado' en los primeros meses frente a la covid-19 y sobre el que m\u00e1s estudios se han hecho. https:\/\/t.co\/63rZzKbpMo https:\/\/t.co\/LXBj2M3IU7"},"user_verified":{"0":false,"1":false,"2":false,"3":false,"4":false,"5":false,"6":false,"7":false,"8":false,"9":false,"10":false,"11":false,"12":false,"13":false,"14":false,"15":false,"16":false,"17":false,"18":false,"19":false,"20":false,"21":false,"22":false,"23":false,"24":false,"25":false,"26":false,"27":false,"28":false,"29":false,"30":false,"31":false,"32":false,"33":false},"created_at":{"0":"2020-11-03 22:50:03","1":"2020-11-03 21:50:02","2":"2020-11-03 20:50:02","3":"2020-11-03 20:21:08","4":"2020-11-03 20:18:14","5":"2020-11-03 20:16:05","6":"2020-11-03 20:08:34","7":"2020-11-03 20:05:17","8":"2020-11-03 20:02:11","9":"2020-11-03 19:59:29","10":"2020-11-03 19:51:44","11":"2020-11-03 19:50:07","12":"2020-11-03 19:48:21","13":"2020-11-03 19:45:09","14":"2020-11-03 19:41:11","15":"2020-11-03 19:29:23","16":"2020-11-03 19:25:16","17":"2020-11-03 19:18:27","18":"2020-11-03 19:16:50","19":"2020-11-03 19:12:37","20":"2020-11-03 18:53:27","21":"2020-11-03 18:50:02","22":"2020-11-03 16:50:05","23":"2020-11-03 15:50:02","24":"2020-11-03 14:50:02","25":"2020-11-03 13:50:02","26":"2020-11-03 12:50:08","27":"2020-11-03 11:50:02","28":"2020-11-03 10:50:03","29":"2020-11-03 09:50:04","30":"2020-11-03 08:50:03","31":"2020-11-03 07:50:03","32":"2020-11-03 06:50:02","33":"2020-11-03 06:00:38"},"retweet_count":{"0":2,"1":0,"2":2,"3":1,"4":0,"5":6,"6":1,"7":1,"8":0,"9":4,"10":1,"11":1,"12":1,"13":0,"14":1,"15":2,"16":0,"17":1,"18":2,"19":1,"20":2,"21":0,"22":2,"23":0,"24":3,"25":2,"26":3,"27":0,"28":1,"29":0,"30":1,"31":0,"32":2,"33":3},"favorite_count":{"0":2,"1":0,"2":1,"3":3,"4":1,"5":9,"6":4,"7":3,"8":1,"9":12,"10":1,"11":2,"12":2,"13":3,"14":2,"15":3,"16":3,"17":3,"18":1,"19":4,"20":3,"21":0,"22":1,"23":1,"24":9,"25":4,"26":1,"27":1,"28":3,"29":0,"30":2,"31":0,"32":4,"33":0},"user_location":{"0":"Madrid","1":"Madrid","2":"Madrid","3":"Madrid","4":"Madrid","5":"Madrid","6":"Madrid","7":"Madrid","8":"Madrid","9":"Madrid","10":"Madrid","11":"Madrid","12":"Madrid","13":"Madrid","14":"Madrid","15":"Madrid","16":"Madrid","17":"Madrid","18":"Madrid","19":"Madrid","20":"Madrid","21":"Madrid","22":"Madrid","23":"Madrid","24":"Madrid","25":"Madrid","26":"Madrid","27":"Madrid","28":"Madrid","29":"Madrid","30":"Madrid","31":"Madrid","32":"Madrid","33":"Madrid"},"user_url":{"0":"http:\/\/t.co\/9yU5u7xTRr","1":"http:\/\/t.co\/9yU5u7xTRr","2":"http:\/\/t.co\/9yU5u7xTRr","3":"http:\/\/t.co\/9yU5u7xTRr","4":"http:\/\/t.co\/9yU5u7xTRr","5":"http:\/\/t.co\/9yU5u7xTRr","6":"http:\/\/t.co\/9yU5u7xTRr","7":"http:\/\/t.co\/9yU5u7xTRr","8":"http:\/\/t.co\/9yU5u7xTRr","9":"http:\/\/t.co\/9yU5u7xTRr","10":"http:\/\/t.co\/9yU5u7xTRr","11":"http:\/\/t.co\/9yU5u7xTRr","12":"http:\/\/t.co\/9yU5u7xTRr","13":"http:\/\/t.co\/9yU5u7xTRr","14":"http:\/\/t.co\/9yU5u7xTRr","15":"http:\/\/t.co\/9yU5u7xTRr","16":"http:\/\/t.co\/9yU5u7xTRr","17":"http:\/\/t.co\/9yU5u7xTRr","18":"http:\/\/t.co\/9yU5u7xTRr","19":"http:\/\/t.co\/9yU5u7xTRr","20":"http:\/\/t.co\/9yU5u7xTRr","21":"http:\/\/t.co\/9yU5u7xTRr","22":"http:\/\/t.co\/9yU5u7xTRr","23":"http:\/\/t.co\/9yU5u7xTRr","24":"http:\/\/t.co\/9yU5u7xTRr","25":"http:\/\/t.co\/9yU5u7xTRr","26":"http:\/\/t.co\/9yU5u7xTRr","27":"http:\/\/t.co\/9yU5u7xTRr","28":"http:\/\/t.co\/9yU5u7xTRr","29":"http:\/\/t.co\/9yU5u7xTRr","30":"http:\/\/t.co\/9yU5u7xTRr","31":"http:\/\/t.co\/9yU5u7xTRr","32":"http:\/\/t.co\/9yU5u7xTRr","33":"http:\/\/t.co\/9yU5u7xTRr"},"entities":{"0":{"hashtags":[{"text":"Empresas","indices":[0,9]}],"symbols":[],"user_mentions":[{"screen_name":"Novartis","name":"Novartis","id":17226612,"id_str":"17226612","indices":[67,76]}],"urls":[{"url":"https:\/\/t.co\/3kwiRVSx4I","expanded_url":"https:\/\/bit.ly\/35ZARNR","display_url":"bit.ly\/35ZARNR","indices":[207,230]}],"media":[{"id":1323759370426089473,"id_str":"1323759370426089473","indices":[231,254],"media_url":"http:\/\/pbs.twimg.com\/media\/El7wIkJXgAExTgx.jpg","media_url_https":"https:\/\/pbs.twimg.com\/media\/El7wIkJXgAExTgx.jpg","url":"https:\/\/t.co\/HG0jBLwe1c","display_url":"pic.twitter.com\/HG0jBLwe1c","expanded_url":"https:\/\/twitter.com\/diariomedico\/status\/1323759371898290178\/photo\/1","type":"photo","sizes":{"thumb":{"w":150,"h":150,"resize":"crop"},"small":{"w":680,"h":453,"resize":"fit"},"medium":{"w":1200,"h":800,"resize":"fit"},"large":{"w":1200,"h":800,"resize":"fit"}}}]},"1":{"hashtags":[{"text":"COVID19","indices":[0,8]}],"symbols":[],"user_mentions":[{"screen_name":"amytsmedicos","name":"M\u00e9dicos y TS-Madrid","id":311988179,"id_str":"311988179","indices":[11,24]},{"screen_name":"SaludMadrid","name":"SaludMadrid","id":953996688670314496,"id_str":"953996688670314496","indices":[119,131]},{"screen_name":"frangoiri","name":"Francisco Goiri","id":116472975,"id_str":"116472975","indices":[136,146]},{"screen_name":"jezquerra57","name":"Julian Ezquerra","id":605670192,"id_str":"605670192","indices":[147,159]},{"screen_name":"eruizescudero","name":"Enrique Ruiz Escudero","id":209171395,"id_str":"209171395","indices":[160,174]},{"screen_name":"SheilajustoS","name":"sheilajusto","id":708998715118370817,"id_str":"708998715118370817","indices":[175,188]},{"screen_name":"tki_ojo","name":"Angela Hern\u00e1ndez Puente \ud83d\ude37","id":276192868,"id_str":"276192868","indices":[189,197]},{"screen_name":"TomasToranzo1","name":"Tomas Toranzo Cepeda","id":390707379,"id_str":"390707379","indices":[198,212]},{"screen_name":"cesm_sindicatos","name":"CESM #PonteLaMascarilla","id":2589440382,"id_str":"2589440382","indices":[213,229]},{"screen_name":"mlalanda","name":"M\u00f3nica Lalanda","id":83467126,"id_str":"83467126","indices":[230,239]}],"urls":[{"url":"https:\/\/t.co\/t9UCCNAdSo","expanded_url":"https:\/\/bit.ly\/3kSi79i","display_url":"bit.ly\/3kSi79i","indices":[240,263]}],"media":[{"id":1323744269820219392,"id_str":"1323744269820219392","indices":[264,287],"media_url":"http:\/\/pbs.twimg.com\/media\/El7iZmAX0AAddYx.jpg","media_url_https":"https:\/\/pbs.twimg.com\/media\/El7iZmAX0AAddYx.jpg","url":"https:\/\/t.co\/WXCyp8PT1I","display_url":"pic.twitter.com\/WXCyp8PT1I","expanded_url":"https:\/\/twitter.com\/diariomedico\/status\/1323744271309164546\/photo\/1","type":"photo","sizes":{"thumb":{"w":150,"h":150,"resize":"crop"},"large":{"w":1200,"h":800,"resize":"fit"},"medium":{"w":1200,"h":800,"resize":"fit"},"small":{"w":680,"h":453,"resize":"fit"}}}]},"2":{"hashtags":[],"symbols":[],"user_mentions":[],"urls":[{"url":"https:\/\/t.co\/kOR2ITux00","expanded_url":"https:\/\/bit.ly\/360MB2B","display_url":"bit.ly\/360MB2B","indices":[237,260]}],"media":[{"id":1323729168618692609,"id_str":"1323729168618692609","indices":[261,284],"media_url":"http:\/\/pbs.twimg.com\/media\/El7UqlpXIAEUwh1.jpg","media_url_https":"https:\/\/pbs.twimg.com\/media\/El7UqlpXIAEUwh1.jpg","url":"https:\/\/t.co\/tZDCTqOhMq","display_url":"pic.twitter.com\/tZDCTqOhMq","expanded_url":"https:\/\/twitter.com\/diariomedico\/status\/1323729170392899586\/photo\/1","type":"photo","sizes":{"small":{"w":680,"h":453,"resize":"fit"},"thumb":{"w":150,"h":150,"resize":"crop"},"large":{"w":1200,"h":800,"resize":"fit"},"medium":{"w":1200,"h":800,"resize":"fit"}}}]},"3":{"hashtags":[{"text":"Admirables","indices":[0,11]}],"symbols":[],"user_mentions":[{"screen_name":"SromeroOmc","name":"Serafin Romero","id":418547173,"id_str":"418547173","indices":[15,26]}],"urls":[]},"4":{"hashtags":[{"text":"Admirables","indices":[0,11]}],"symbols":[],"user_mentions":[{"screen_name":"SromeroOmc","name":"Serafin Romero","id":418547173,"id_str":"418547173","indices":[14,25]}],"urls":[]},"5":{"hashtags":[{"text":"Admirables","indices":[0,11]}],"symbols":[],"user_mentions":[{"screen_name":"SromeroOmc","name":"Serafin Romero","id":418547173,"id_str":"418547173","indices":[39,50]},{"screen_name":"OMC_Espana","name":"Organizaci\u00f3n M\u00e9dica Colegial #AMMCordoba2020","id":425703865,"id_str":"425703865","indices":[66,77]}],"urls":[],"media":[{"id":1323720625635139585,"id_str":"1323720625635139585","indices":[198,221],"media_url":"http:\/\/pbs.twimg.com\/media\/El7M5UjXIAEeKyZ.jpg","media_url_https":"https:\/\/pbs.twimg.com\/media\/El7M5UjXIAEeKyZ.jpg","url":"https:\/\/t.co\/5CbQmhOZay","display_url":"pic.twitter.com\/5CbQmhOZay","expanded_url":"https:\/\/twitter.com\/diariomedico\/status\/1323720627170217985\/photo\/1","type":"photo","sizes":{"thumb":{"w":150,"h":150,"resize":"crop"},"medium":{"w":1024,"h":768,"resize":"fit"},"small":{"w":680,"h":510,"resize":"fit"},"large":{"w":1024,"h":768,"resize":"fit"}}}]},"6":{"hashtags":[{"text":"Admirables","indices":[0,11]}],"symbols":[],"user_mentions":[],"urls":[],"media":[{"id":1323718734607953928,"id_str":"1323718734607953928","indices":[281,304],"media_url":"http:\/\/pbs.twimg.com\/media\/El7LLP7WMAghcuj.jpg","media_url_https":"https:\/\/pbs.twimg.com\/media\/El7LLP7WMAghcuj.jpg","url":"https:\/\/t.co\/ZefIeQAJ1F","display_url":"pic.twitter.com\/ZefIeQAJ1F","expanded_url":"https:\/\/twitter.com\/diariomedico\/status\/1323718736675774466\/photo\/1","type":"photo","sizes":{"large":{"w":1620,"h":1080,"resize":"fit"},"thumb":{"w":150,"h":150,"resize":"crop"},"small":{"w":680,"h":453,"resize":"fit"},"medium":{"w":1200,"h":800,"resize":"fit"}}}]},"7":{"hashtags":[{"text":"Admirables","indices":[0,11]}],"symbols":[],"user_mentions":[{"screen_name":"PresidenteCGCOF","name":"Jes\u00fas Aguilar","id":3318745156,"id_str":"3318745156","indices":[28,44]},{"screen_name":"Farmaceuticos_","name":"Farmac\u00e9uticos","id":115653126,"id_str":"115653126","indices":[88,103]}],"urls":[],"media":[{"id":1323717905750642689,"id_str":"1323717905750642689","indices":[242,265],"media_url":"http:\/\/pbs.twimg.com\/media\/El7KbAMXUAEeDWS.jpg","media_url_https":"https:\/\/pbs.twimg.com\/media\/El7KbAMXUAEeDWS.jpg","url":"https:\/\/t.co\/pLnEqeZ1Ed","display_url":"pic.twitter.com\/pLnEqeZ1Ed","expanded_url":"https:\/\/twitter.com\/diariomedico\/status\/1323717907537403907\/photo\/1","type":"photo","sizes":{"small":{"w":680,"h":510,"resize":"fit"},"thumb":{"w":150,"h":150,"resize":"crop"},"large":{"w":1600,"h":1200,"resize":"fit"},"medium":{"w":1200,"h":900,"resize":"fit"}}}]},"8":{"hashtags":[{"text":"Admirables","indices":[0,11]}],"symbols":[],"user_mentions":[{"screen_name":"GileadSciences","name":"Gilead Sciences","id":309728693,"id_str":"309728693","indices":[55,70]}],"urls":[]},"9":{"hashtags":[{"text":"Admirables","indices":[0,11]}],"symbols":[],"user_mentions":[{"screen_name":"CGEnfermeria","name":"Consejo General de Enfermer\u00eda","id":223315961,"id_str":"223315961","indices":[50,63]}],"urls":[],"media":[{"id":1323716445570801677,"id_str":"1323716445570801677","indices":[233,256],"media_url":"http:\/\/pbs.twimg.com\/media\/El7JGAmXIA0BwGv.jpg","media_url_https":"https:\/\/pbs.twimg.com\/media\/El7JGAmXIA0BwGv.jpg","url":"https:\/\/t.co\/H2r4S344eT","display_url":"pic.twitter.com\/H2r4S344eT","expanded_url":"https:\/\/twitter.com\/diariomedico\/status\/1323716447143690242\/photo\/1","type":"photo","sizes":{"medium":{"w":1024,"h":768,"resize":"fit"},"thumb":{"w":150,"h":150,"resize":"crop"},"small":{"w":680,"h":510,"resize":"fit"},"large":{"w":1024,"h":768,"resize":"fit"}}}]},"10":{"hashtags":[{"text":"Admirables","indices":[0,11]}],"symbols":[],"user_mentions":[{"screen_name":"BidaFarma","name":"Bidafarma","id":728237763041103872,"id_str":"728237763041103872","indices":[31,41]}],"urls":[]},"11":{"hashtags":[{"text":"MedSafetyWeek","indices":[0,14]},{"text":"medicamentos","indices":[89,102]}],"symbols":[],"user_mentions":[{"screen_name":"AEMPSGOB","name":"AEMPS","id":326845755,"id_str":"326845755","indices":[17,26]}],"urls":[{"url":"https:\/\/t.co\/KZAvV3nWUN","expanded_url":"https:\/\/bit.ly\/34Qenj3","display_url":"bit.ly\/34Qenj3","indices":[125,148]}],"media":[{"id":1323714090158665734,"id_str":"1323714090158665734","indices":[149,172],"media_url":"http:\/\/pbs.twimg.com\/media\/El7G86AWMAY1BvK.jpg","media_url_https":"https:\/\/pbs.twimg.com\/media\/El7G86AWMAY1BvK.jpg","url":"https:\/\/t.co\/LDYaMRauHu","display_url":"pic.twitter.com\/LDYaMRauHu","expanded_url":"https:\/\/twitter.com\/diariomedico\/status\/1323714091836493831\/photo\/1","type":"photo","sizes":{"thumb":{"w":150,"h":150,"resize":"crop"},"large":{"w":1200,"h":800,"resize":"fit"},"small":{"w":680,"h":453,"resize":"fit"},"medium":{"w":1200,"h":800,"resize":"fit"}}}]},"12":{"hashtags":[{"text":"Admirables","indices":[0,11]}],"symbols":[],"user_mentions":[{"screen_name":"magomore","name":"Mago More","id":49077697,"id_str":"49077697","indices":[84,93]}],"urls":[],"media":[{"id":1323713646980177923,"id_str":"1323713646980177923","indices":[94,117],"media_url":"http:\/\/pbs.twimg.com\/media\/El7GjHCXIAMepMw.jpg","media_url_https":"https:\/\/pbs.twimg.com\/media\/El7GjHCXIAMepMw.jpg","url":"https:\/\/t.co\/ESTv0BlhUx","display_url":"pic.twitter.com\/ESTv0BlhUx","expanded_url":"https:\/\/twitter.com\/diariomedico\/status\/1323713648565620741\/photo\/1","type":"photo","sizes":{"thumb":{"w":150,"h":150,"resize":"crop"},"medium":{"w":1200,"h":900,"resize":"fit"},"large":{"w":1600,"h":1200,"resize":"fit"},"small":{"w":680,"h":510,"resize":"fit"}}}]},"13":{"hashtags":[{"text":"Admirables","indices":[78,89]}],"symbols":[],"user_mentions":[{"screen_name":"magomore","name":"Mago More","id":49077697,"id_str":"49077697","indices":[22,31]}],"urls":[],"media":[{"id":1323712838163173376,"id_str":"1323712838163173376","indices":[174,197],"media_url":"http:\/\/pbs.twimg.com\/media\/El7F0B9XEAAlaSf.jpg","media_url_https":"https:\/\/pbs.twimg.com\/media\/El7F0B9XEAAlaSf.jpg","url":"https:\/\/t.co\/MeFO8QmdGi","display_url":"pic.twitter.com\/MeFO8QmdGi","expanded_url":"https:\/\/twitter.com\/diariomedico\/status\/1323712839710838785\/photo\/1","type":"photo","sizes":{"thumb":{"w":150,"h":150,"resize":"crop"},"small":{"w":680,"h":453,"resize":"fit"},"large":{"w":1398,"h":932,"resize":"fit"},"medium":{"w":1200,"h":800,"resize":"fit"}}}]},"14":{"hashtags":[{"text":"Admirables","indices":[35,46]}],"symbols":[],"user_mentions":[{"screen_name":"magomore","name":"Mago More","id":49077697,"id_str":"49077697","indices":[14,23]}],"urls":[],"media":[{"id":1323711842125008897,"id_str":"1323711842125008897","indices":[127,150],"media_url":"http:\/\/pbs.twimg.com\/media\/El7E6DbW0AEkeQ9.jpg","media_url_https":"https:\/\/pbs.twimg.com\/media\/El7E6DbW0AEkeQ9.jpg","url":"https:\/\/t.co\/saZRuufN7L","display_url":"pic.twitter.com\/saZRuufN7L","expanded_url":"https:\/\/twitter.com\/diariomedico\/status\/1323711843538472960\/photo\/1","type":"photo","sizes":{"thumb":{"w":150,"h":150,"resize":"crop"},"large":{"w":1306,"h":872,"resize":"fit"},"small":{"w":680,"h":454,"resize":"fit"},"medium":{"w":1200,"h":801,"resize":"fit"}}}]},"15":{"hashtags":[{"text":"admirables","indices":[240,251]}],"symbols":[],"user_mentions":[],"urls":[],"media":[{"id":1323708870850760705,"id_str":"1323708870850760705","indices":[253,276],"media_url":"http:\/\/pbs.twimg.com\/media\/El7CNGkX0AEdisp.jpg","media_url_https":"https:\/\/pbs.twimg.com\/media\/El7CNGkX0AEdisp.jpg","url":"https:\/\/t.co\/Zwq9daydBL","display_url":"pic.twitter.com\/Zwq9daydBL","expanded_url":"https:\/\/twitter.com\/diariomedico\/status\/1323708872767508480\/photo\/1","type":"photo","sizes":{"thumb":{"w":150,"h":150,"resize":"crop"},"large":{"w":1620,"h":1080,"resize":"fit"},"small":{"w":680,"h":453,"resize":"fit"},"medium":{"w":1200,"h":800,"resize":"fit"}}}]},"16":{"hashtags":[{"text":"Admirables","indices":[0,11]}],"symbols":[],"user_mentions":[{"screen_name":"miguelgcorral","name":"Miguel G. Corral","id":216056423,"id_str":"216056423","indices":[27,41]}],"urls":[],"media":[{"id":1323707833997758465,"id_str":"1323707833997758465","indices":[111,134],"media_url":"http:\/\/pbs.twimg.com\/media\/El7BQv_WkAENBZh.jpg","media_url_https":"https:\/\/pbs.twimg.com\/media\/El7BQv_WkAENBZh.jpg","url":"https:\/\/t.co\/krwubs98cq","display_url":"pic.twitter.com\/krwubs98cq","expanded_url":"https:\/\/twitter.com\/diariomedico\/status\/1323707835772010496\/photo\/1","type":"photo","sizes":{"thumb":{"w":150,"h":150,"resize":"crop"},"small":{"w":680,"h":453,"resize":"fit"},"large":{"w":1599,"h":1066,"resize":"fit"},"medium":{"w":1200,"h":800,"resize":"fit"}}}]},"17":{"hashtags":[{"text":"Admirables","indices":[0,11]}],"symbols":[],"user_mentions":[{"screen_name":"unidadeditorial","name":"Unidad Editorial","id":57620993,"id_str":"57620993","indices":[55,71]}],"urls":[],"media":[{"id":1323706122340048896,"id_str":"1323706122340048896","indices":[236,259],"media_url":"http:\/\/pbs.twimg.com\/media\/El6_tHkWoAAZWwc.jpg","media_url_https":"https:\/\/pbs.twimg.com\/media\/El6_tHkWoAAZWwc.jpg","url":"https:\/\/t.co\/AxkbRq4iIB","display_url":"pic.twitter.com\/AxkbRq4iIB","expanded_url":"https:\/\/twitter.com\/diariomedico\/status\/1323706124223324172\/photo\/1","type":"photo","sizes":{"thumb":{"w":150,"h":150,"resize":"crop"},"small":{"w":510,"h":680,"resize":"fit"},"large":{"w":1200,"h":1600,"resize":"fit"},"medium":{"w":900,"h":1200,"resize":"fit"}}}]},"18":{"hashtags":[{"text":"COVID19","indices":[0,8]}],"symbols":[],"user_mentions":[],"urls":[{"url":"https:\/\/t.co\/LTAsYOSd2v","expanded_url":"https:\/\/bit.ly\/2GoRiuq","display_url":"bit.ly\/2GoRiuq","indices":[94,117]}],"media":[{"id":1323705712418131968,"id_str":"1323705712418131968","indices":[118,141],"media_url":"http:\/\/pbs.twimg.com\/media\/El6_VQfWkAAq-Nq.jpg","media_url_https":"https:\/\/pbs.twimg.com\/media\/El6_VQfWkAAq-Nq.jpg","url":"https:\/\/t.co\/L41nlWJE5q","display_url":"pic.twitter.com\/L41nlWJE5q","expanded_url":"https:\/\/twitter.com\/diariomedico\/status\/1323705714225930240\/photo\/1","type":"photo","sizes":{"thumb":{"w":150,"h":150,"resize":"crop"},"medium":{"w":1200,"h":800,"resize":"fit"},"small":{"w":680,"h":453,"resize":"fit"},"large":{"w":1200,"h":800,"resize":"fit"}}}]},"19":{"hashtags":[{"text":"Admirables","indices":[0,11]}],"symbols":[],"user_mentions":[{"screen_name":"miguelgcorral","name":"Miguel G. Corral","id":216056423,"id_str":"216056423","indices":[35,49]},{"screen_name":"unidadeditorial","name":"Unidad Editorial","id":57620993,"id_str":"57620993","indices":[81,97]}],"urls":[],"media":[{"id":1323704651519303681,"id_str":"1323704651519303681","indices":[138,161],"media_url":"http:\/\/pbs.twimg.com\/media\/El6-XgVXIAEMg7Q.jpg","media_url_https":"https:\/\/pbs.twimg.com\/media\/El6-XgVXIAEMg7Q.jpg","url":"https:\/\/t.co\/XXAUncWFpJ","display_url":"pic.twitter.com\/XXAUncWFpJ","expanded_url":"https:\/\/twitter.com\/diariomedico\/status\/1323704653268328448\/photo\/1","type":"photo","sizes":{"thumb":{"w":150,"h":150,"resize":"crop"},"large":{"w":1600,"h":1200,"resize":"fit"},"small":{"w":680,"h":510,"resize":"fit"},"medium":{"w":1200,"h":900,"resize":"fit"}}}]},"20":{"hashtags":[],"symbols":[],"user_mentions":[],"urls":[{"url":"https:\/\/t.co\/WWN9mVlZMk","expanded_url":"https:\/\/twitter.com\/unidadeditorial\/status\/1323693572462419970","display_url":"twitter.com\/unidadeditoria\u2026","indices":[36,59]}]},"21":{"hashtags":[{"text":"COVID19","indices":[0,8]}],"symbols":[],"user_mentions":[],"urls":[{"url":"https:\/\/t.co\/RVdjGmEBA8","expanded_url":"https:\/\/bit.ly\/2HSFvF8","display_url":"bit.ly\/2HSFvF8","indices":[185,208]}],"media":[{"id":1323698970586218506,"id_str":"1323698970586218506","indices":[209,232],"media_url":"http:\/\/pbs.twimg.com\/media\/El65M1NXgAo8HUN.jpg","media_url_https":"https:\/\/pbs.twimg.com\/media\/El65M1NXgAo8HUN.jpg","url":"https:\/\/t.co\/oHxTAFgden","display_url":"pic.twitter.com\/oHxTAFgden","expanded_url":"https:\/\/twitter.com\/diariomedico\/status\/1323698971953549314\/photo\/1","type":"photo","sizes":{"thumb":{"w":150,"h":150,"resize":"crop"},"medium":{"w":1200,"h":800,"resize":"fit"},"large":{"w":1200,"h":800,"resize":"fit"},"small":{"w":680,"h":453,"resize":"fit"}}}]},"22":{"hashtags":[{"text":"estadodealarmaesp","indices":[5,23]}],"symbols":[],"user_mentions":[{"screen_name":"sespas","name":"SESPAS","id":721740028393734144,"id_str":"721740028393734144","indices":[146,153]},{"screen_name":"saldeana","name":"soledad valle amaro","id":226710931,"id_str":"226710931","indices":[177,186]}],"urls":[{"url":"https:\/\/t.co\/U7FgF6tcwH","expanded_url":"https:\/\/bit.ly\/3ekAeCg","display_url":"bit.ly\/3ekAeCg","indices":[188,211]}],"media":[{"id":1323668781705666562,"id_str":"1323668781705666562","indices":[212,235],"media_url":"http:\/\/pbs.twimg.com\/media\/El6dvm3XIAIz-18.jpg","media_url_https":"https:\/\/pbs.twimg.com\/media\/El6dvm3XIAIz-18.jpg","url":"https:\/\/t.co\/FtixX2aYfj","display_url":"pic.twitter.com\/FtixX2aYfj","expanded_url":"https:\/\/twitter.com\/diariomedico\/status\/1323668783257526273\/photo\/1","type":"photo","sizes":{"thumb":{"w":150,"h":150,"resize":"crop"},"small":{"w":680,"h":453,"resize":"fit"},"large":{"w":1200,"h":800,"resize":"fit"},"medium":{"w":1200,"h":800,"resize":"fit"}}}]},"23":{"hashtags":[{"text":"COVID19","indices":[0,8]}],"symbols":[],"user_mentions":[{"screen_name":"salvadorilla","name":"Salvador Illa Roca\/\u2764\ufe0f","id":233240412,"id_str":"233240412","indices":[11,24]},{"screen_name":"GobAsturias","name":"Gobierno de Asturias","id":890838088443977728,"id_str":"890838088443977728","indices":[97,109]}],"urls":[{"url":"https:\/\/t.co\/idbUTVDqvL","expanded_url":"https:\/\/bit.ly\/35XBI1L","display_url":"bit.ly\/35XBI1L","indices":[173,196]}],"media":[{"id":1323653672488886274,"id_str":"1323653672488886274","indices":[197,220],"media_url":"http:\/\/pbs.twimg.com\/media\/El6QAIpXYAIrZ9P.jpg","media_url_https":"https:\/\/pbs.twimg.com\/media\/El6QAIpXYAIrZ9P.jpg","url":"https:\/\/t.co\/wdAFS9TU9r","display_url":"pic.twitter.com\/wdAFS9TU9r","expanded_url":"https:\/\/twitter.com\/diariomedico\/status\/1323653674279854081\/photo\/1","type":"photo","sizes":{"thumb":{"w":150,"h":150,"resize":"crop"},"large":{"w":1200,"h":800,"resize":"fit"},"small":{"w":680,"h":453,"resize":"fit"},"medium":{"w":1200,"h":800,"resize":"fit"}}}]},"24":{"hashtags":[{"text":"COVID19","indices":[143,151]}],"symbols":[],"user_mentions":[{"screen_name":"IdiazAyuso","name":"Isabel D\u00edaz Ayuso","id":140034129,"id_str":"140034129","indices":[1,12]},{"screen_name":"ComunidadMadrid","name":"Comunidad de Madrid","id":122353251,"id_str":"122353251","indices":[28,44]},{"screen_name":"AEMPSGOB","name":"AEMPS","id":326845755,"id_str":"326845755","indices":[70,79]},{"screen_name":"COFMadrid","name":"COF Madrid","id":863676390,"id_str":"863676390","indices":[183,193]}],"urls":[{"url":"https:\/\/t.co\/eRnS0gbMC9","expanded_url":"https:\/\/bit.ly\/2Gsk3GK","display_url":"bit.ly\/2Gsk3GK","indices":[194,217]}],"media":[{"id":1323638570528198656,"id_str":"1323638570528198656","indices":[218,241],"media_url":"http:\/\/pbs.twimg.com\/media\/El6CRFdW0AANDia.jpg","media_url_https":"https:\/\/pbs.twimg.com\/media\/El6CRFdW0AANDia.jpg","url":"https:\/\/t.co\/6AIGhCtZ67","display_url":"pic.twitter.com\/6AIGhCtZ67","expanded_url":"https:\/\/twitter.com\/diariomedico\/status\/1323638572033937408\/photo\/1","type":"photo","sizes":{"thumb":{"w":150,"h":150,"resize":"crop"},"medium":{"w":1200,"h":800,"resize":"fit"},"small":{"w":680,"h":453,"resize":"fit"},"large":{"w":1200,"h":800,"resize":"fit"}}}]},"25":{"hashtags":[{"text":"LABCLIN2020","indices":[0,12]},{"text":"COVID19","indices":[76,84]}],"symbols":[],"user_mentions":[{"screen_name":"congresolabclin","name":"Laboratorio Cl\u00ednico","id":1299406016,"id_str":"1299406016","indices":[86,102]},{"screen_name":"yoyobustelo","name":"Manuel F. Bustelo","id":247252792,"id_str":"247252792","indices":[113,125]}],"urls":[{"url":"https:\/\/t.co\/f4NgTh5siN","expanded_url":"https:\/\/bit.ly\/3mUanEB","display_url":"bit.ly\/3mUanEB","indices":[132,155]}],"media":[{"id":1323623472451457025,"id_str":"1323623472451457025","indices":[156,179],"media_url":"http:\/\/pbs.twimg.com\/media\/El50iQvWkAELGNR.jpg","media_url_https":"https:\/\/pbs.twimg.com\/media\/El50iQvWkAELGNR.jpg","url":"https:\/\/t.co\/erpTSxXLKG","display_url":"pic.twitter.com\/erpTSxXLKG","expanded_url":"https:\/\/twitter.com\/diariomedico\/status\/1323623473835630593\/photo\/1","type":"photo","sizes":{"large":{"w":1200,"h":800,"resize":"fit"},"thumb":{"w":150,"h":150,"resize":"crop"},"medium":{"w":1200,"h":800,"resize":"fit"},"small":{"w":680,"h":453,"resize":"fit"}}}]},"26":{"hashtags":[{"text":"COVID19","indices":[54,62]}],"symbols":[],"user_mentions":[{"screen_name":"Sociedad_SEMI","name":"Sociedad Espa\u00f1ola de Medicina Interna (SEMI)","id":2545613263,"id_str":"2545613263","indices":[84,98]}],"urls":[{"url":"https:\/\/t.co\/dTUasfdGw6","expanded_url":"https:\/\/bit.ly\/32plRYX","display_url":"bit.ly\/32plRYX","indices":[116,139]}],"media":[{"id":1323608398026428416,"id_str":"1323608398026428416","indices":[140,163],"media_url":"http:\/\/pbs.twimg.com\/media\/El5m00IW0AAaPDC.jpg","media_url_https":"https:\/\/pbs.twimg.com\/media\/El5m00IW0AAaPDC.jpg","url":"https:\/\/t.co\/OWGKHQP5oV","display_url":"pic.twitter.com\/OWGKHQP5oV","expanded_url":"https:\/\/twitter.com\/diariomedico\/status\/1323608399607701510\/photo\/1","type":"photo","sizes":{"thumb":{"w":150,"h":150,"resize":"crop"},"small":{"w":680,"h":453,"resize":"fit"},"medium":{"w":1200,"h":800,"resize":"fit"},"large":{"w":1200,"h":800,"resize":"fit"}}}]},"27":{"hashtags":[{"text":"CAR","indices":[121,125]}],"symbols":[],"user_mentions":[{"screen_name":"sehh_es","name":"@sehh_es","id":3253853525,"id_str":"3253853525","indices":[36,44]}],"urls":[{"url":"https:\/\/t.co\/nVk0oKkHo7","expanded_url":"https:\/\/bit.ly\/2JtcxfL","display_url":"bit.ly\/2JtcxfL","indices":[173,196]}],"media":[{"id":1323593271151644672,"id_str":"1323593271151644672","indices":[197,220],"media_url":"http:\/\/pbs.twimg.com\/media\/El5ZEUIXUAAyEuU.jpg","media_url_https":"https:\/\/pbs.twimg.com\/media\/El5ZEUIXUAAyEuU.jpg","url":"https:\/\/t.co\/3fXjTaNmJL","display_url":"pic.twitter.com\/3fXjTaNmJL","expanded_url":"https:\/\/twitter.com\/diariomedico\/status\/1323593272812515328\/photo\/1","type":"photo","sizes":{"thumb":{"w":150,"h":150,"resize":"crop"},"medium":{"w":1200,"h":800,"resize":"fit"},"small":{"w":680,"h":453,"resize":"fit"},"large":{"w":1200,"h":800,"resize":"fit"}}}]},"28":{"hashtags":[],"symbols":[],"user_mentions":[{"screen_name":"AshoOficial","name":"ASHO","id":963186782706765824,"id_str":"963186782706765824","indices":[12,24]}],"urls":[{"url":"https:\/\/t.co\/3Zew8zAZOb","expanded_url":"https:\/\/bit.ly\/3jFXZpp","display_url":"bit.ly\/3jFXZpp","indices":[67,90]}],"media":[{"id":1323578176954605568,"id_str":"1323578176954605568","indices":[91,114],"media_url":"http:\/\/pbs.twimg.com\/media\/El5LVt3WoAAgXVa.jpg","media_url_https":"https:\/\/pbs.twimg.com\/media\/El5LVt3WoAAgXVa.jpg","url":"https:\/\/t.co\/NLNNSbXZWQ","display_url":"pic.twitter.com\/NLNNSbXZWQ","expanded_url":"https:\/\/twitter.com\/diariomedico\/status\/1323578178552647680\/photo\/1","type":"photo","sizes":{"thumb":{"w":150,"h":150,"resize":"crop"},"medium":{"w":1200,"h":800,"resize":"fit"},"large":{"w":1200,"h":800,"resize":"fit"},"small":{"w":680,"h":453,"resize":"fit"}}}]},"29":{"hashtags":[{"text":"atresia","indices":[35,43]}],"symbols":[],"user_mentions":[],"urls":[{"url":"https:\/\/t.co\/dujTwiPvpo","expanded_url":"https:\/\/bit.ly\/35TGm0E","display_url":"bit.ly\/35TGm0E","indices":[102,125]}],"media":[{"id":1323563081247657984,"id_str":"1323563081247657984","indices":[126,149],"media_url":"http:\/\/pbs.twimg.com\/media\/El49nB-WkAAPghL.jpg","media_url_https":"https:\/\/pbs.twimg.com\/media\/El49nB-WkAAPghL.jpg","url":"https:\/\/t.co\/kQOzS8mgRw","display_url":"pic.twitter.com\/kQOzS8mgRw","expanded_url":"https:\/\/twitter.com\/diariomedico\/status\/1323563083864920065\/photo\/1","type":"photo","sizes":{"large":{"w":1200,"h":800,"resize":"fit"},"thumb":{"w":150,"h":150,"resize":"crop"},"medium":{"w":1200,"h":800,"resize":"fit"},"small":{"w":680,"h":453,"resize":"fit"}}}]},"30":{"hashtags":[{"text":"Admirables","indices":[0,11]},{"text":"COVID19","indices":[103,111]}],"symbols":[],"user_mentions":[{"screen_name":"Fepimcti","name":"Fepimcti","id":538147097,"id_str":"538147097","indices":[48,57]}],"urls":[{"url":"https:\/\/t.co\/huUTSJ3yoI","expanded_url":"https:\/\/bit.ly\/3kRzEhS","display_url":"bit.ly\/3kRzEhS","indices":[126,149]}],"media":[{"id":1323547977076645888,"id_str":"1323547977076645888","indices":[150,173],"media_url":"http:\/\/pbs.twimg.com\/media\/El4v32jXIAAqtC7.jpg","media_url_https":"https:\/\/pbs.twimg.com\/media\/El4v32jXIAAqtC7.jpg","url":"https:\/\/t.co\/Liks6uuvFY","display_url":"pic.twitter.com\/Liks6uuvFY","expanded_url":"https:\/\/twitter.com\/diariomedico\/status\/1323547978318176257\/photo\/1","type":"photo","sizes":{"thumb":{"w":150,"h":150,"resize":"crop"},"small":{"w":680,"h":453,"resize":"fit"},"medium":{"w":1200,"h":800,"resize":"fit"},"large":{"w":1200,"h":800,"resize":"fit"}}}]},"31":{"hashtags":[{"text":"LaConsultaDM","indices":[0,13]}],"symbols":[],"user_mentions":[],"urls":[{"url":"https:\/\/t.co\/tfZ1BQrJ5x","expanded_url":"https:\/\/bit.ly\/3ejutFa","display_url":"bit.ly\/3ejutFa","indices":[78,101]}],"media":[{"id":1323532877989109760,"id_str":"1323532877989109760","indices":[102,125],"media_url":"http:\/\/pbs.twimg.com\/media\/El4iI-EXYAAL7xC.jpg","media_url_https":"https:\/\/pbs.twimg.com\/media\/El4iI-EXYAAL7xC.jpg","url":"https:\/\/t.co\/ZG72uyTacD","display_url":"pic.twitter.com\/ZG72uyTacD","expanded_url":"https:\/\/twitter.com\/diariomedico\/status\/1323532879448735744\/photo\/1","type":"photo","sizes":{"small":{"w":680,"h":453,"resize":"fit"},"thumb":{"w":150,"h":150,"resize":"crop"},"large":{"w":1200,"h":800,"resize":"fit"},"medium":{"w":1200,"h":800,"resize":"fit"}}}]},"32":{"hashtags":[{"text":"Admirables","indices":[0,11]}],"symbols":[],"user_mentions":[{"screen_name":"aserranogomez","name":"Alicia Serrano G\u00f3mez","id":464858825,"id_str":"464858825","indices":[249,263]}],"urls":[{"url":"https:\/\/t.co\/Wh1L4TOCaq","expanded_url":"https:\/\/bit.ly\/3kJhO0B","display_url":"bit.ly\/3kJhO0B","indices":[221,244]}],"media":[{"id":1323517775638372357,"id_str":"1323517775638372357","indices":[264,287],"media_url":"http:\/\/pbs.twimg.com\/media\/El4UZ5bXIAU2ZOq.jpg","media_url_https":"https:\/\/pbs.twimg.com\/media\/El4UZ5bXIAU2ZOq.jpg","url":"https:\/\/t.co\/D5rW643z3q","display_url":"pic.twitter.com\/D5rW643z3q","expanded_url":"https:\/\/twitter.com\/diariomedico\/status\/1323517777181888513\/photo\/1","type":"photo","sizes":{"thumb":{"w":150,"h":150,"resize":"crop"},"large":{"w":1200,"h":800,"resize":"fit"},"medium":{"w":1200,"h":800,"resize":"fit"},"small":{"w":680,"h":453,"resize":"fit"}}}]},"33":{"hashtags":[],"symbols":[],"user_mentions":[],"urls":[{"url":"https:\/\/t.co\/63rZzKbpMo","expanded_url":"https:\/\/bit.ly\/323tSCD","display_url":"bit.ly\/323tSCD","indices":[160,183]}],"media":[{"id":1323505342404349955,"id_str":"1323505342404349955","indices":[184,207],"media_url":"http:\/\/pbs.twimg.com\/media\/El4JGMBX0AMz74o.jpg","media_url_https":"https:\/\/pbs.twimg.com\/media\/El4JGMBX0AMz74o.jpg","url":"https:\/\/t.co\/LXBj2M3IU7","display_url":"pic.twitter.com\/LXBj2M3IU7","expanded_url":"https:\/\/twitter.com\/diariomedico\/status\/1323505343817748485\/photo\/1","type":"photo","sizes":{"thumb":{"w":150,"h":150,"resize":"crop"},"medium":{"w":1200,"h":800,"resize":"fit"},"large":{"w":1200,"h":800,"resize":"fit"},"small":{"w":680,"h":453,"resize":"fit"}}}]}}}